jupyterlab_tensorboard_pro/__init__.py
jupyterlab_tensorboard_pro/api_handlers.py
jupyterlab_tensorboard_pro/handlers.py
jupyterlab_tensorboard_pro/tensorboard_manager.py
jupyterlab_tensorboard_pro/__pycache__/__init__.cpython-38.pyc
jupyterlab_tensorboard_pro/__pycache__/handlers.cpython-38.pyc
jupyterlab_tensorboard_pro/labextension/package.json
jupyterlab_tensorboard_pro/labextension/static/179.6d30c85cc0fef3819b0c.js
jupyterlab_tensorboard_pro/labextension/static/184.079d3e4ea819d1120b64.js
jupyterlab_tensorboard_pro/labextension/static/184.079d3e4ea819d1120b64.js.LICENSE.txt
jupyterlab_tensorboard_pro/labextension/static/20ab106935cc98542a78.eot
jupyterlab_tensorboard_pro/labextension/static/22cad8fab69528828c08.woff
jupyterlab_tensorboard_pro/labextension/static/3211ded00f0b3264f9df.woff2
jupyterlab_tensorboard_pro/labextension/static/38.256c9a9a8d0e0f9c8923.js
jupyterlab_tensorboard_pro/labextension/static/3e7ec16041075151625b.woff2
jupyterlab_tensorboard_pro/labextension/static/411.670d8bb5f129e3d7e7c8.js
jupyterlab_tensorboard_pro/labextension/static/445.235d5c254fb2fe82ba98.js
jupyterlab_tensorboard_pro/labextension/static/445.b13c280039614b254fcd.js
jupyterlab_tensorboard_pro/labextension/static/445.bc2e18b338e7fa8f9bf8.js
jupyterlab_tensorboard_pro/labextension/static/445.db9be928fa98a57b3a9e.js
jupyterlab_tensorboard_pro/labextension/static/445.e9c98b7f3cb39766ca5c.js
jupyterlab_tensorboard_pro/labextension/static/445.f4d009ce820e01bc9e3a.js
jupyterlab_tensorboard_pro/labextension/static/513.f33b8240c13d4aa10cda.js
jupyterlab_tensorboard_pro/labextension/static/554.705a010ef1c16e3d9fe2.js
jupyterlab_tensorboard_pro/labextension/static/569.cb44dbf24e972b0ccaa8.js
jupyterlab_tensorboard_pro/labextension/static/595.6f1629fbb28c08d5bec9.js
jupyterlab_tensorboard_pro/labextension/static/610.421ba93fb1085f06d617.js
jupyterlab_tensorboard_pro/labextension/static/674.332b94913cec73e4842b.js
jupyterlab_tensorboard_pro-4.0.0.dist-info/LICENSE
jupyterlab_tensorboard_pro-4.0.0.dist-info/METADATA
jupyterlab_tensorboard_pro-4.0.0.dist-info/WHEEL
jupyterlab_tensorboard_pro-4.0.0.dist-info/entry_points.txt
jupyterlab_tensorboard_pro-4.0.0.dist-info/top_level.txt
jupyterlab_tensorboard_pro-4.0.0.dist-info/RECORD
