Metadata-Version: 2.1
Name: jupyterlab-tensorboard-pro
Version: 4.0.0
Summary: A JupyterLab extension for tensorboard.
Home-page: https://github.com/HFAiLab/jupyterlab_tensorboard_pro
Author: aircloud
Author-email: onlythen@yeah.net
License: MIT
Keywords: Jupyter,JupyterLab,JupyterLab3,Tensorboard,Tensorflow
Platform: Linux
Platform: Mac OS X
Platform: Windows
Classifier: Intended Audience :: Developers
Classifier: Intended Audience :: Science/Research
Classifier: License :: OSI Approved :: BSD License
Classifier: Programming Language :: Python
Classifier: Programming Language :: Python :: 3
Classifier: Programming Language :: Python :: 3.6
Classifier: Programming Language :: Python :: 3.7
Classifier: Programming Language :: Python :: 3.8
Classifier: Programming Language :: Python :: 3.9
Classifier: Programming Language :: Python :: 3.10
Classifier: Framework :: Jupyter
Requires-Python: >=3.6
License-File: LICENSE
Requires-Dist: jupyterlab >=4.0
Requires-Dist: tornado <=6.2
